flask_cuttlepool.py
Flask_CuttlePool-0.2.1.dist-info/LICENSE
Flask_CuttlePool-0.2.1.dist-info/METADATA
Flask_CuttlePool-0.2.1.dist-info/WHEEL
Flask_CuttlePool-0.2.1.dist-info/top_level.txt
Flask_CuttlePool-0.2.1.dist-info/RECORD
