Metadata-Version: 2.1
Name: Flask-CuttlePool
Version: 0.2.1
Summary: A Flask extension for CuttlePool
Home-page: http://github.com/smitchell556/flask-cuttlepool
Author: Spencer Mitchell
License: BSD 3-Clause
Platform: any
Classifier: Environment :: Web Environment
Classifier: Intended Audience :: Developers
Classifier: License :: OSI Approved :: BSD License
Classifier: Operating System :: OS Independent
Classifier: Programming Language :: Python
Classifier: Topic :: Internet :: WWW/HTTP :: Dynamic Content
Classifier: Topic :: Software Development :: Libraries :: Python Modules
Requires-Dist: cuttlepool (==0.6.0)
Requires-Dist: flask
Provides-Extra: dev
Requires-Dist: pytest ; extra == 'dev'
